scaff/__init__.py
scaff/compat.py
scaff/templates/python/.gitignore
scaff/templates/python/MANIFEST.in
scaff/templates/python/README.rst
scaff/templates/python/setup.cfg
scaff/templates/python/setup.py
scaff/templates/python/tox.ini
scaff/templates/python/doc/index.html
scaff/templates/python/requirements/doc.txt
scaff/templates/python/requirements/install.txt
scaff/templates/python/requirements/test.txt
scaff/templates/python/src/namespace/__init__.py
scaff/templates/python/src/namespace/package/__init__.py
scaff/templates/python/src/namespace/package/version.txt
scaff/templates/python/src/namespace/package/tests/__init__.py
scaff-0.2.0.dist-info/DESCRIPTION.rst
scaff-0.2.0.dist-info/entry_points.txt
scaff-0.2.0.dist-info/METADATA
scaff-0.2.0.dist-info/metadata.json
scaff-0.2.0.dist-info/RECORD
scaff-0.2.0.dist-info/top_level.txt
scaff-0.2.0.dist-info/WHEEL
scaff-0.2.0.dist-info/zip-safe
