Metadata-Version: 2.0
Name: scaff
Version: 0.2.0
Summary: I'm sorry, I also I have made a scaffolding tool.
Home-page: https://github.com/TakesxiSximada/scaff
Author: TakesxiSximada
Author-email: takesxi.sximada@gmail.com
License: BSD
Download-URL: https://github.com/TakesxiSximada/scaff
Platform: any
Classifier: Development Status :: 1 - Planning
Classifier: Intended Audience :: Developers
Classifier: Intended Audience :: Information Technology
Classifier: Intended Audience :: System Administrators
Classifier: License :: OSI Approved :: BSD License
Classifier: Natural Language :: English
Classifier: Natural Language :: Japanese
Classifier: Operating System :: MacOS :: MacOS X
Classifier: Operating System :: Microsoft :: Windows
Classifier: Operating System :: POSIX
Classifier: Programming Language :: Python :: 3.4
Requires-Dist: mako
Requires-Dist: six
